Metadata-Version: 2.1
Name: sessioner-globally.scoped
Version: 0.0.5
Summary: A soon-to-be cool project.
Author: g-scope (Globally Scoped)
Author-email: 
Keywords: python,session,sessioner,cryptography,security,tool
Classifier: Intended Audience :: Developers
Classifier: Programming Language :: Python :: 3
Classifier: Operating System :: Unix
Classifier: Operating System :: MacOS :: MacOS X
Classifier: Operating System :: Microsoft :: Windows
License-File: LICENSE.md
